PBM_SUPPORT_DF_WINDOW.py
alerting_subsystem.py
dataframe_timeseries_mon/__init__.py
dataframe_timeseries_mon/alerting.py
dataframe_timeseries_mon/cli.py
dataframe_timeseries_mon/df_window.py
dataframe_timeseries_mon-1.0.1.dist-info/licenses/LICENSE
dataframe_timeseries_mon-1.0.1.dist-info/METADATA
dataframe_timeseries_mon-1.0.1.dist-info/WHEEL
dataframe_timeseries_mon-1.0.1.dist-info/top_level.txt
dataframe_timeseries_mon-1.0.1.dist-info/RECORD
