Metadata-Version: 2.4
Name: Dataframe-timeseries-mon
Version: 1.0.1
Summary: DataFrame ordered-window extraction with diagnostics and an envvar-based monitoring integration layer
Author: Marcin Kowalczyk
License: MIT
Keywords: pandas,timeseries,monitoring,alerting,environment-variables,dataframe,etl
Classifier: License :: OSI Approved :: MIT License
Classifier: Programming Language :: Python :: 3
Classifier: Programming Language :: Python :: 3 :: Only
Classifier: Programming Language :: Python :: 3.9
Classifier: Programming Language :: Python :: 3.10
Classifier: Programming Language :: Python :: 3.11
Classifier: Programming Language :: Python :: 3.12
Classifier: Operating System :: OS Independent
Classifier: Intended Audience :: Developers
Classifier: Topic :: Scientific/Engineering
Classifier: Topic :: System :: Monitoring
Requires-Python: >=3.9
License-File: LICENSE
Requires-Dist: pandas>=1.5
Provides-Extra: dev
Requires-Dist: build>=1.0; extra == "dev"
Requires-Dist: twine>=5.0; extra == "dev"
Dynamic: license-file
